<annotation>
  <filename>000108.png</filename>
  <folder>VOC2007</folder>
  <object>
    <bndbox>
      <xmax>2982</xmax>
      <xmin>2977</xmin>
      <ymax>1220</ymax>
      <ymin>1</ymin>
    </bndbox>
    <difficult>0</difficult>
    <name>wv_cw</name>
    <pose>unspecified</pose>
    <truncated>0</truncated>
  </object>
  <object>
    <bndbox>
      <xmax>2081</xmax>
      <xmin>1990</xmin>
      <ymax>1220</ymax>
      <ymin>0</ymin>
    </bndbox>
    <difficult>0</difficult>
    <name>wv_wbfm</name>
    <pose>unspecified</pose>
    <truncated>0</truncated>
  </object>
  <object>
    <bndbox>
      <xmax>3215</xmax>
      <xmin>3210</xmin>
      <ymax>1009</ymax>
      <ymin>1006</ymin>
    </bndbox>
    <difficult>0</difficult>
    <name>wv_usb</name>
    <pose>unspecified</pose>
    <truncated>0</truncated>
  </object>
  <object>
    <bndbox>
      <xmax>3215</xmax>
      <xmin>3210</xmin>
      <ymax>1002</ymax>
      <ymin>993</ymin>
    </bndbox>
    <difficult>0</difficult>
    <name>wv_usb</name>
    <pose>unspecified</pose>
    <truncated>0</truncated>
  </object>
  <object>
    <bndbox>
      <xmax>3215</xmax>
      <xmin>3210</xmin>
      <ymax>989</ymax>
      <ymin>947</ymin>
    </bndbox>
    <difficult>0</difficult>
    <name>wv_usb</name>
    <pose>unspecified</pose>
    <truncated>0</truncated>
  </object>
  <object>
    <bndbox>
      <xmax>3215</xmax>
      <xmin>3210</xmin>
      <ymax>946</ymax>
      <ymin>940</ymin>
    </bndbox>
    <difficult>0</difficult>
    <name>wv_usb</name>
    <pose>unspecified</pose>
    <truncated>0</truncated>
  </object>
  <object>
    <bndbox>
      <xmax>3215</xmax>
      <xmin>3210</xmin>
      <ymax>939</ymax>
      <ymin>930</ymin>
    </bndbox>
    <difficult>0</difficult>
    <name>wv_usb</name>
    <pose>unspecified</pose>
    <truncated>0</truncated>
  </object>
  <object>
    <bndbox>
      <xmax>3215</xmax>
      <xmin>3210</xmin>
      <ymax>929</ymax>
      <ymin>908</ymin>
    </bndbox>
    <difficult>0</difficult>
    <name>wv_usb</name>
    <pose>unspecified</pose>
    <truncated>0</truncated>
  </object>
  <object>
    <bndbox>
      <xmax>3215</xmax>
      <xmin>3210</xmin>
      <ymax>907</ymax>
      <ymin>881</ymin>
    </bndbox>
    <difficult>0</difficult>
    <name>wv_usb</name>
    <pose>unspecified</pose>
    <truncated>0</truncated>
  </object>
  <object>
    <bndbox>
      <xmax>3215</xmax>
      <xmin>3210</xmin>
      <ymax>880</ymax>
      <ymin>843</ymin>
    </bndbox>
    <difficult>0</difficult>
    <name>wv_usb</name>
    <pose>unspecified</pose>
    <truncated>0</truncated>
  </object>
  <object>
    <bndbox>
      <xmax>3215</xmax>
      <xmin>3210</xmin>
      <ymax>842</ymax>
      <ymin>808</ymin>
    </bndbox>
    <difficult>0</difficult>
    <name>wv_usb</name>
    <pose>unspecified</pose>
    <truncated>0</truncated>
  </object>
  <object>
    <bndbox>
      <xmax>3215</xmax>
      <xmin>3210</xmin>
      <ymax>807</ymax>
      <ymin>774</ymin>
    </bndbox>
    <difficult>0</difficult>
    <name>wv_usb</name>
    <pose>unspecified</pose>
    <truncated>0</truncated>
  </object>
  <object>
    <bndbox>
      <xmax>3583</xmax>
      <xmin>3578</xmin>
      <ymax>1220</ymax>
      <ymin>786</ymin>
    </bndbox>
    <difficult>0</difficult>
    <name>wv_am</name>
    <pose>unspecified</pose>
    <truncated>0</truncated>
  </object>
  <object>
    <bndbox>
      <xmax>3215</xmax>
      <xmin>3210</xmin>
      <ymax>773</ymax>
      <ymin>758</ymin>
    </bndbox>
    <difficult>0</difficult>
    <name>wv_usb</name>
    <pose>unspecified</pose>
    <truncated>0</truncated>
  </object>
  <object>
    <bndbox>
      <xmax>3215</xmax>
      <xmin>3210</xmin>
      <ymax>757</ymax>
      <ymin>747</ymin>
    </bndbox>
    <difficult>0</difficult>
    <name>wv_usb</name>
    <pose>unspecified</pose>
    <truncated>0</truncated>
  </object>
  <object>
    <bndbox>
      <xmax>3215</xmax>
      <xmin>3210</xmin>
      <ymax>746</ymax>
      <ymin>588</ymin>
    </bndbox>
    <difficult>0</difficult>
    <name>wv_usb</name>
    <pose>unspecified</pose>
    <truncated>0</truncated>
  </object>
  <object>
    <bndbox>
      <xmax>3215</xmax>
      <xmin>3210</xmin>
      <ymax>587</ymax>
      <ymin>582</ymin>
    </bndbox>
    <difficult>0</difficult>
    <name>wv_usb</name>
    <pose>unspecified</pose>
    <truncated>0</truncated>
  </object>
  <object>
    <bndbox>
      <xmax>3215</xmax>
      <xmin>3210</xmin>
      <ymax>581</ymax>
      <ymin>560</ymin>
    </bndbox>
    <difficult>0</difficult>
    <name>wv_usb</name>
    <pose>unspecified</pose>
    <truncated>0</truncated>
  </object>
  <object>
    <bndbox>
      <xmax>3215</xmax>
      <xmin>3210</xmin>
      <ymax>559</ymax>
      <ymin>521</ymin>
    </bndbox>
    <difficult>0</difficult>
    <name>wv_usb</name>
    <pose>unspecified</pose>
    <truncated>0</truncated>
  </object>
  <object>
    <bndbox>
      <xmax>3215</xmax>
      <xmin>3210</xmin>
      <ymax>520</ymax>
      <ymin>516</ymin>
    </bndbox>
    <difficult>0</difficult>
    <name>wv_usb</name>
    <pose>unspecified</pose>
    <truncated>0</truncated>
  </object>
  <object>
    <bndbox>
      <xmax>3215</xmax>
      <xmin>3210</xmin>
      <ymax>515</ymax>
      <ymin>501</ymin>
    </bndbox>
    <difficult>0</difficult>
    <name>wv_usb</name>
    <pose>unspecified</pose>
    <truncated>0</truncated>
  </object>
  <object>
    <bndbox>
      <xmax>3215</xmax>
      <xmin>3210</xmin>
      <ymax>500</ymax>
      <ymin>476</ymin>
    </bndbox>
    <difficult>0</difficult>
    <name>wv_usb</name>
    <pose>unspecified</pose>
    <truncated>0</truncated>
  </object>
  <object>
    <bndbox>
      <xmax>3215</xmax>
      <xmin>3210</xmin>
      <ymax>475</ymax>
      <ymin>469</ymin>
    </bndbox>
    <difficult>0</difficult>
    <name>wv_usb</name>
    <pose>unspecified</pose>
    <truncated>0</truncated>
  </object>
  <object>
    <bndbox>
      <xmax>3583</xmax>
      <xmin>3578</xmin>
      <ymax>778</ymax>
      <ymin>741</ymin>
    </bndbox>
    <difficult>0</difficult>
    <name>wv_am</name>
    <pose>unspecified</pose>
    <truncated>0</truncated>
  </object>
  <object>
    <bndbox>
      <xmax>3215</xmax>
      <xmin>3210</xmin>
      <ymax>468</ymax>
      <ymin>455</ymin>
    </bndbox>
    <difficult>0</difficult>
    <name>wv_usb</name>
    <pose>unspecified</pose>
    <truncated>0</truncated>
  </object>
  <object>
    <bndbox>
      <xmax>3215</xmax>
      <xmin>3210</xmin>
      <ymax>454</ymax>
      <ymin>420</ymin>
    </bndbox>
    <difficult>0</difficult>
    <name>wv_usb</name>
    <pose>unspecified</pose>
    <truncated>0</truncated>
  </object>
  <object>
    <bndbox>
      <xmax>3215</xmax>
      <xmin>3210</xmin>
      <ymax>419</ymax>
      <ymin>414</ymin>
    </bndbox>
    <difficult>0</difficult>
    <name>wv_usb</name>
    <pose>unspecified</pose>
    <truncated>0</truncated>
  </object>
  <object>
    <bndbox>
      <xmax>3215</xmax>
      <xmin>3210</xmin>
      <ymax>413</ymax>
      <ymin>383</ymin>
    </bndbox>
    <difficult>0</difficult>
    <name>wv_usb</name>
    <pose>unspecified</pose>
    <truncated>0</truncated>
  </object>
  <object>
    <bndbox>
      <xmax>3215</xmax>
      <xmin>3210</xmin>
      <ymax>382</ymax>
      <ymin>364</ymin>
    </bndbox>
    <difficult>0</difficult>
    <name>wv_usb</name>
    <pose>unspecified</pose>
    <truncated>0</truncated>
  </object>
  <object>
    <bndbox>
      <xmax>3215</xmax>
      <xmin>3210</xmin>
      <ymax>363</ymax>
      <ymin>336</ymin>
    </bndbox>
    <difficult>0</difficult>
    <name>wv_usb</name>
    <pose>unspecified</pose>
    <truncated>0</truncated>
  </object>
  <object>
    <bndbox>
      <xmax>3215</xmax>
      <xmin>3209</xmin>
      <ymax>335</ymax>
      <ymin>132</ymin>
    </bndbox>
    <difficult>0</difficult>
    <name>wv_usb</name>
    <pose>unspecified</pose>
    <truncated>0</truncated>
  </object>
  <object>
    <bndbox>
      <xmax>3214</xmax>
      <xmin>3211</xmin>
      <ymax>131</ymax>
      <ymin>127</ymin>
    </bndbox>
    <difficult>0</difficult>
    <name>wv_usb</name>
    <pose>unspecified</pose>
    <truncated>0</truncated>
  </object>
  <object>
    <bndbox>
      <xmax>3214</xmax>
      <xmin>3210</xmin>
      <ymax>126</ymax>
      <ymin>114</ymin>
    </bndbox>
    <difficult>0</difficult>
    <name>wv_usb</name>
    <pose>unspecified</pose>
    <truncated>0</truncated>
  </object>
  <object>
    <bndbox>
      <xmax>3214</xmax>
      <xmin>3211</xmin>
      <ymax>111</ymax>
      <ymin>107</ymin>
    </bndbox>
    <difficult>0</difficult>
    <name>wv_usb</name>
    <pose>unspecified</pose>
    <truncated>0</truncated>
  </object>
  <object>
    <bndbox>
      <xmax>3583</xmax>
      <xmin>3578</xmin>
      <ymax>724</ymax>
      <ymin>697</ymin>
    </bndbox>
    <difficult>0</difficult>
    <name>wv_am</name>
    <pose>unspecified</pose>
    <truncated>0</truncated>
  </object>
  <object>
    <bndbox>
      <xmax>3214</xmax>
      <xmin>3210</xmin>
      <ymax>105</ymax>
      <ymin>99</ymin>
    </bndbox>
    <difficult>0</difficult>
    <name>wv_usb</name>
    <pose>unspecified</pose>
    <truncated>0</truncated>
  </object>
  <object>
    <bndbox>
      <xmax>3214</xmax>
      <xmin>3211</xmin>
      <ymax>97</ymax>
      <ymin>94</ymin>
    </bndbox>
    <difficult>0</difficult>
    <name>wv_usb</name>
    <pose>unspecified</pose>
    <truncated>0</truncated>
  </object>
  <object>
    <bndbox>
      <xmax>3214</xmax>
      <xmin>3210</xmin>
      <ymax>93</ymax>
      <ymin>87</ymin>
    </bndbox>
    <difficult>0</difficult>
    <name>wv_usb</name>
    <pose>unspecified</pose>
    <truncated>0</truncated>
  </object>
  <object>
    <bndbox>
      <xmax>3214</xmax>
      <xmin>3210</xmin>
      <ymax>86</ymax>
      <ymin>62</ymin>
    </bndbox>
    <difficult>0</difficult>
    <name>wv_usb</name>
    <pose>unspecified</pose>
    <truncated>0</truncated>
  </object>
  <object>
    <bndbox>
      <xmax>3214</xmax>
      <xmin>3210</xmin>
      <ymax>61</ymax>
      <ymin>45</ymin>
    </bndbox>
    <difficult>0</difficult>
    <name>wv_usb</name>
    <pose>unspecified</pose>
    <truncated>0</truncated>
  </object>
  <object>
    <bndbox>
      <xmax>3214</xmax>
      <xmin>3210</xmin>
      <ymax>43</ymax>
      <ymin>32</ymin>
    </bndbox>
    <difficult>0</difficult>
    <name>wv_usb</name>
    <pose>unspecified</pose>
    <truncated>0</truncated>
  </object>
  <object>
    <bndbox>
      <xmax>3214</xmax>
      <xmin>3210</xmin>
      <ymax>28</ymax>
      <ymin>14</ymin>
    </bndbox>
    <difficult>0</difficult>
    <name>wv_usb</name>
    <pose>unspecified</pose>
    <truncated>0</truncated>
  </object>
  <object>
    <bndbox>
      <xmax>3461</xmax>
      <xmin>3455</xmin>
      <ymax>1220</ymax>
      <ymin>1</ymin>
    </bndbox>
    <difficult>0</difficult>
    <name>wv_cw</name>
    <pose>unspecified</pose>
    <truncated>0</truncated>
  </object>
  <object>
    <bndbox>
      <xmax>3583</xmax>
      <xmin>3578</xmin>
      <ymax>686</ymax>
      <ymin>1</ymin>
    </bndbox>
    <difficult>0</difficult>
    <name>wv_am</name>
    <pose>unspecified</pose>
    <truncated>0</truncated>
  </object>
  <object>
    <bndbox>
      <xmax>3215</xmax>
      <xmin>3210</xmin>
      <ymax>1220</ymax>
      <ymin>1111</ymin>
    </bndbox>
    <difficult>0</difficult>
    <name>wv_usb</name>
    <pose>unspecified</pose>
    <truncated>0</truncated>
  </object>
  <object>
    <bndbox>
      <xmax>3215</xmax>
      <xmin>3210</xmin>
      <ymax>1110</ymax>
      <ymin>1069</ymin>
    </bndbox>
    <difficult>0</difficult>
    <name>wv_usb</name>
    <pose>unspecified</pose>
    <truncated>0</truncated>
  </object>
  <object>
    <bndbox>
      <xmax>3215</xmax>
      <xmin>3210</xmin>
      <ymax>1068</ymax>
      <ymin>1045</ymin>
    </bndbox>
    <difficult>0</difficult>
    <name>wv_usb</name>
    <pose>unspecified</pose>
    <truncated>0</truncated>
  </object>
  <object>
    <bndbox>
      <xmax>3215</xmax>
      <xmin>3210</xmin>
      <ymax>1044</ymax>
      <ymin>1010</ymin>
    </bndbox>
    <difficult>0</difficult>
    <name>wv_usb</name>
    <pose>unspecified</pose>
    <truncated>0</truncated>
  </object>
  <segmented>False</segmented>
  <size>
    <depth>1</depth>
    <height>1220</height>
    <width>4096</width>
  </size>
</annotation>