<annotation>
  <filename>000283.png</filename>
  <folder>VOC2007</folder>
  <object>
    <bndbox>
      <xmax>1162</xmax>
      <xmin>1157</xmin>
      <ymax>263</ymax>
      <ymin>0</ymin>
    </bndbox>
    <difficult>0</difficult>
    <name>wv_cw</name>
    <pose>unspecified</pose>
    <truncated>0</truncated>
  </object>
  <object>
    <bndbox>
      <xmax>206</xmax>
      <xmin>184</xmin>
      <ymax>266</ymax>
      <ymin>0</ymin>
    </bndbox>
    <difficult>0</difficult>
    <name>wv_wbfm</name>
    <pose>unspecified</pose>
    <truncated>0</truncated>
  </object>
  <object>
    <bndbox>
      <xmax>964</xmax>
      <xmin>942</xmin>
      <ymax>266</ymax>
      <ymin>0</ymin>
    </bndbox>
    <difficult>0</difficult>
    <name>wv_wbfm</name>
    <pose>unspecified</pose>
    <truncated>0</truncated>
  </object>
  <object>
    <bndbox>
      <xmax>1104</xmax>
      <xmin>1098</xmin>
      <ymax>266</ymax>
      <ymin>0</ymin>
    </bndbox>
    <difficult>0</difficult>
    <name>wv_cw</name>
    <pose>unspecified</pose>
    <truncated>0</truncated>
  </object>
  <segmented>False</segmented>
  <size>
    <depth>1</depth>
    <height>267</height>
    <width>2048</width>
  </size>
</annotation>